benchmark_adv_ml/.ipynb_checkpoints/ClusteringSurvival-checkpoint.py
benchmark_adv_ml/.ipynb_checkpoints/__main__-checkpoint.py
benchmark_adv_ml/.ipynb_checkpoints/autoencoder-checkpoint.py
benchmark_adv_ml/.ipynb_checkpoints/benchmark_ml-checkpoint.py
benchmark_adv_ml/.ipynb_checkpoints/classification_model_stability_test-checkpoint.py
benchmark_adv_ml/.ipynb_checkpoints/make_plots-checkpoint.py
benchmark_adv_ml/.ipynb_checkpoints/make_temp_data-checkpoint.py
benchmark_adv_ml/.ipynb_checkpoints/pre_processing-checkpoint.py
benchmark_adv_ml/.ipynb_checkpoints/result_process-checkpoint.py
benchmark_adv_ml/.ipynb_checkpoints/temp_dataset-checkpoint.csv
benchmark_adv_ml/.ipynb_checkpoints/train_autoencoder-checkpoint.py
benchmark_adv_ml/.~lock.temp_dataset.csv#
benchmark_adv_ml/ClusteringSurvival.py
benchmark_adv_ml/__init__.py
benchmark_adv_ml/__main__.py
benchmark_adv_ml/autoencoder.py
benchmark_adv_ml/benchmark_ml.py
benchmark_adv_ml/classification_model_stability_test.py
benchmark_adv_ml/evaluate_extract_ae.py
benchmark_adv_ml/make_plots.py
benchmark_adv_ml/make_temp_data.py
benchmark_adv_ml/pre_processing.py
benchmark_adv_ml/predict_clusters.py
benchmark_adv_ml/process_clustered_data.py
benchmark_adv_ml/result_process.py
benchmark_adv_ml/temp_dataset.csv
benchmark_adv_ml/train_autoencoder.py
benchmark_adv_ml-0.2.8.dist-info/LICENSE
benchmark_adv_ml-0.2.8.dist-info/METADATA
benchmark_adv_ml-0.2.8.dist-info/WHEEL
benchmark_adv_ml-0.2.8.dist-info/entry_points.txt
benchmark_adv_ml-0.2.8.dist-info/RECORD
